egGTFS/__init__.py
egGTFS/egGTFS.py
egGTFS/samples/ex_busHeatMap.py
egGTFS/samples/ex_drawAllRoute.py
egGTFS/samples/ex_drawTrip.py
egGTFS/samples/ex_filter.py
egGTFS/samples/ex_makeAllBusStopsHTML.py
egGTFS/samples/ex_makeShapeHTML.py
egGTFS-2.1.2.dist-info/LICENSE
egGTFS-2.1.2.dist-info/METADATA
egGTFS-2.1.2.dist-info/WHEEL
egGTFS-2.1.2.dist-info/top_level.txt
egGTFS-2.1.2.dist-info/RECORD
